{
  "parent": "minecraft:recipes/root",
  "rewards": {
    "recipes": [
      "backmath:tiara_de_gato"
    ]
  },
  "criteria": {
    "has_cat_tiara": {
      "trigger": "minecraft:inventory_changed",
      "conditions": {
        "items": [
          {
            "item": "minecraft:blue_wool"
          }
        ]
      }
    },
    "has_the_recipe": {
      "trigger": "minecraft:recipe_unlocked",
      "conditions": {
        "recipe": "backmath:cat_tiara"
      }
    }
  },
  "requirements": [
    [
      "has_cat_tiara",
      "has_the_recipe"
    ]
  ]
}