{
  "parent": "minecraft:recipes/root",
  "rewards": {
    "recipes": [
      "backmath:golden_halo"
    ]
  },
  "criteria": {
    "has_gold_nuggets": {
      "trigger": "minecraft:inventory_changed",
      "conditions": {
        "items": [
          {
            "tag": "forge:nuggets/gold"
          }
        ]
      }
    },
    "has_the_recipe": {
      "trigger": "minecraft:recipe_unlocked",
      "conditions": {
        "recipe": "backmath:golden_halo"
      }
    }
  },
  "requirements": [
    [
      "has_gold_nuggets",
      "has_the_recipe"
    ]
  ]
}